azkm/__init__.py
azkm/__main__.py
azkm/cdktf.json
azkm/commands/__init__.py
azkm/commands/dataset.py
azkm/commands/deploy.py
azkm/commands/destroy.py
azkm/commands/environment.py
azkm/commands/environments.py
azkm/commands/init.py
azkm/commands/recipe.py
azkm/commands/state.py
azkm/commands/version.py
azkm/flight_checks/__init__.py
azkm/flight_checks/prereqs.py
azkm/providers/__init__.py
azkm/providers/azurerm/__init__.py
azkm/providers/azurerm/_jsii/__init__.py
azkm/providers/azurerm/_jsii/azurerm@0.0.0.jsii.tgz
azkm/utils/__init__.py
azkm/utils/aks.py
azkm/utils/app.py
azkm/utils/az.py
azkm/utils/cogsearch.py
azkm/utils/osutil.py
azkm/utils/stdout.py
azkm/utils/text.py
azkm/utils/tf.py
azkm/utils/zip.py
azkm-0.2.71.dist-info/LICENSE
azkm-0.2.71.dist-info/METADATA
azkm-0.2.71.dist-info/WHEEL
azkm-0.2.71.dist-info/entry_points.txt
azkm-0.2.71.dist-info/top_level.txt
azkm-0.2.71.dist-info/RECORD
